{"data":{"\u767b\u8a18\u6a5f\u95dc":"\u9ad8\u96c4\u5e02\u653f\u5e9c\u7d93\u6fdf\u767c\u5c55\u5c40","\u6838\u51c6\u8a2d\u7acb\u65e5\u671f":{"year":2008,"month":7,"day":14},"\u5546\u696d\u540d\u7a31":"\u767b\u5bcc\u767c\u7167\u660e\u79d1\u6280\u4f01\u696d\u793e","\u8ca0\u8cac\u4eba\u59d3\u540d":"\u6d82\u9293\u7950","\u73fe\u6cc1":"\u6838\u51c6\u8a2d\u7acb","\u8cc7\u672c\u984d(\u5143)":"5,000,000","\u7d44\u7e54\u985e\u578b":"\u7368\u8cc7","\u5730\u5740":"\u9ad8\u96c4\u5e02\u4ec1\u6b66\u5340\u7af9\u5f8c\u91cc\u9cf3\u4ec1\u8def\uff12\uff18\uff17\u4e4b\uff13\uff17\u865f\uff11\u6a13","\u71df\u696d\u9805\u76ee":"1\n\r\n\t\t\t\t\t\t\tCA01100\n\r\n\t\t\t\t\t\t\t\u92c1\u6750\u8ecb\u5ef6\u3001\u4f38\u7dda\u3001\u64e0\u578b\u696d\n\r\n\t\t\t\t\t\t\r\n\t\t\t\t\t\t\t2\n\r\n\t\t\t\t\t\t\tCA01130\n\r\n\t\t\t\t\t\t\t\u9285\u6750\u8ecb\u5ef6\u3001\u4f38\u7dda\u3001\u64e0\u578b\u696d\n\r\n\t\t\t\t\t\t\r\n\t\t\t\t\t\t\t3\n\r\n\t\t\t\t\t\t\tCA02090\n\r\n\t\t\t\t\t\t\t\u91d1\u5c6c\u7dda\u88fd\u54c1\u88fd\u9020\u696d\n\r\n\t\t\t\t\t\t\r\n\t\t\t\t\t\t\t4\n\r\n\t\t\t\t\t\t\tCC01010\n\r\n\t\t\t\t\t\t\t\u767c\u96fb\ufe51\u8f38\u96fb\ufe51\u914d\u96fb\u6a5f\u68b0\u88fd\u9020\u696d\n\r\n\t\t\t\t\t\t\r\n\t\t\t\t\t\t\t5\n\r\n\t\t\t\t\t\t\tCC01020\n\r\n\t\t\t\t\t\t\t\u96fb\u7dda\u53ca\u96fb\u7e9c\u88fd\u9020\u696d\n\r\n\t\t\t\t\t\t\r\n\t\t\t\t\t\t\t6\n\r\n\t\t\t\t\t\t\tCC01040\n\r\n\t\t\t\t\t\t\t\u7167\u660e\u8a2d\u5099\u88fd\u9020\u696d\n\r\n\t\t\t\t\t\t\r\n\t\t\t\t\t\t\t7\n\r\n\t\t\t\t\t\t\tCC01080\n\r\n\t\t\t\t\t\t\t\u96fb\u5b50\u96f6\u7d44\u4ef6\u88fd\u9020\u696d\n\r\n\t\t\t\t\t\t\r\n\t\t\t\t\t\t\t8\n\r\n\t\t\t\t\t\t\tCC01990\n\r\n\t\t\t\t\t\t\t\u5176\u4ed6\u96fb\u6a5f\u53ca\u96fb\u5b50\u6a5f\u68b0\u5668\u6750\u88fd\u9020\u696d\n\r\n\t\t\t\t\t\t\r\n\t\t\t\t\t\t\t9\n\r\n\t\t\t\t\t\t\tCQ01010\n\r\n\t\t\t\t\t\t\t\u6a21\u5177\u88fd\u9020\u696d\n\r\n\t\t\t\t\t\t\r\n\t\t\t\t\t\t\t10\n\r\n\t\t\t\t\t\t\tE603090\n\r\n\t\t\t\t\t\t\t\u7167\u660e\u8a2d\u5099\u5b89\u88dd\u5de5\u7a0b\u696d\uff08\u5728\u5ba2\u6236\u8655\u4f5c\u696d\uff09\n\r\n\t\t\t\t\t\t\r\n\t\t\t\t\t\t\t11\n\r\n\t\t\t\t\t\t\tF113020\n\r\n\t\t\t\t\t\t\t\u96fb\u5668\u6279\u767c\u696d\uff08\u9650\u81ea\u5ee0\u7522\u54c1\uff09\n\r\n\t\t\t\t\t\t\r\n\t\t\t\t\t\t\t12\n\r\n\t\t\t\t\t\t\tF117010\n\r\n\t\t\t\t\t\t\t\u6d88\u9632\u5b89\u5168\u8a2d\u5099\u6279\u767c\u696d\uff08\u9650\u81ea\u5ee0\u7522\u54c1\uff09\n\r\n\t\t\t\t\t\t\r\n\t\t\t\t\t\t\t13\n\r\n\t\t\t\t\t\t\tF118010\n\r\n\t\t\t\t\t\t\t\u8cc7\u8a0a\u8edf\u9ad4\u6279\u767c\u696d\uff08\u9650\u81ea\u5ee0\u7522\u54c1\uff09\n\r\n\t\t\t\t\t\t\r\n\t\t\t\t\t\t\t14\n\r\n\t\t\t\t\t\t\tF119010\n\r\n\t\t\t\t\t\t\t\u96fb\u5b50\u6750\u6599\u6279\u767c\u696d\uff08\u9650\u81ea\u5ee0\u7522\u54c1\uff09","\u51fa\u8cc7\u984d(\u5143)":{"\u6d82\u9293\u7950":"5000000"},"\u7570\u52d5\u6838\u51c6\u65e5\u671f":{"year":2018,"month":4,"day":18},"\u8ca1\u653f\u90e8":{"\u71df\u696d\u4eba\u540d\u7a31":"\u767b\u5bcc\u767c\u7167\u660e\u79d1\u6280\u4f01\u696d\u793e","\u8cc7\u672c\u984d":"5000000","\u8a2d\u7acb\u65e5\u671f":{"year":2008,"month":7,"day":10},"\u4f7f\u7528\u7d71\u4e00\u767c\u7968":"Y","\u884c\u696d":[["284100","\u96fb\u71c8\u6ce1\u53ca\u71c8\u7ba1\u88fd\u9020"],["269911","\u96fb\u5b50\u9023\u63a5\u5668\uff08\u7dda\uff09\u88fd\u9020"],["439099","\u672a\u5206\u985e\u5176\u4ed6\u5c08\u9580\u71df\u9020"],["456112","\u5bb6\u7528\u7167\u660e\u8a2d\u5099\u6279\u767c"]],"\u71df\u696d\u5730\u5740":"\u9ad8\u96c4\u5e02\u4ec1\u6b66\u5340\u7af9\u5f8c\u91cc\u9cf3\u4ec1\u8def\uff12\uff18\uff17\uff0d\uff13\uff17\u865f\uff11\u6a13","\u8ca0\u8cac\u4eba\u59d3\u6c0f":"\u6d82","\u7e3d\u6a5f\u69cb\u7d71\u4e00\u7de8\u865f":"","\u7d44\u7e54\u5225\u540d\u7a31":"\u7368\u8cc7"}}}