{"data":{"\u767b\u8a18\u6a5f\u95dc":"\u81fa\u5357\u5e02\u653f\u5e9c","\u6838\u51c6\u8a2d\u7acb\u65e5\u671f":{"year":2002,"month":9,"day":25},"\u6700\u8fd1\u7570\u52d5\u65e5\u671f":{"year":2006,"month":11,"day":14},"\u5546\u696d\u540d\u7a31":"\u597d\u4e8b\u591a\u6578\u4f4d\u5f71\u50cf\u6574\u5408\u5ee3\u544a\u793e","\u8ca0\u8cac\u4eba\u59d3\u540d":"\u6c5f\u69ae\u76db","\u73fe\u6cc1":"\u6838\u51c6\u8a2d\u7acb","\u8cc7\u672c\u984d(\u5143)":"3,046,000","\u7d44\u7e54\u985e\u578b":"\u7368\u8cc7","\u5730\u5740":"\u81fa\u5357\u5e02\u6771\u5340\u5fe0\u5b5d\u91cc\u4e2d\u83ef\u6771\u8def3\u6bb5470\u865f2\u6a13\uff08\u50c5\u4f9b\u8fa6\u516c\u5ba4\u4f7f\u7528\uff09","\u71df\u696d\u9805\u76ee":"1\r\n\r\n                    E605010\r\n\r\n                    \u96fb\u8166\u8a2d\u5099\u5b89\u88dd\u696d\r\n\r\n              \r\n                    2\r\n\r\n                    I401010\r\n\r\n                    \u4e00\u822c\u5ee3\u544a\u670d\u52d9\u696d\r\n\r\n              \r\n                    3\r\n\r\n                    F113050\r\n\r\n                    \u96fb\u8166\u53ca\u4e8b\u52d9\u6027\u6a5f\u5668\u8a2d\u5099\u6279\u767c\u696d\r\n\r\n              \r\n                    4\r\n\r\n                    IZ10010\r\n\r\n                    \u6392\u7248\u696d\r\n\r\n              \r\n                    5\r\n\r\n                    I501010\r\n\r\n                    \u7522\u54c1\u8a2d\u8a08\u696d\r\n\r\n              \r\n                    6\r\n\r\n                    IZ01010\r\n\r\n                    \u5f71\u5370\u696d\r\n\r\n              \r\n                    7\r\n\r\n                    I301030\r\n\r\n                    \u96fb\u5b50\u8cc7\u8a0a\u4f9b\u61c9\u670d\u52d9\u696d\r\n\r\n              \r\n                    8\r\n\r\n                    F401010\r\n\r\n                    \u570b\u969b\u8cbf\u6613\u696d","\u8ca1\u653f\u90e8":{"\u71df\u696d\u4eba\u540d\u7a31":"\u597d\u4e8b\u591a\u6578\u4f4d\u5f71\u50cf\u6574\u5408\u5ee3\u544a\u793e","\u8cc7\u672c\u984d":"3046000","\u8a2d\u7acb\u65e5\u671f":{"year":2002,"month":9,"day":25},"\u4f7f\u7528\u7d71\u4e00\u767c\u7968":"Y","\u884c\u696d":[["464499","\u5176\u4ed6\u8fa6\u516c\u7528\u6a5f\u68b0\u5668\u5177\u6279\u767c"],["740200","\u5de5\u696d\u8a2d\u8a08"],["483111","\u96fb\u8166\u53ca\u96fb\u8166\u9031\u908a\u8a2d\u5099\u96f6\u552e"],["731099","\u5176\u4ed6\u5ee3\u544a\u670d\u52d9"]],"\u71df\u696d\u5730\u5740":"\u81fa\u5357\u5e02\u6771\u5340\u5fe0\u5b5d\u91cc\u4e2d\u83ef\u6771\u8def\uff13\u6bb5\uff14\uff17\uff10\u865f\uff12\u6a13","\u8ca0\u8cac\u4eba\u59d3\u6c0f":"\u6c5f","\u7e3d\u6a5f\u69cb\u7d71\u4e00\u7de8\u865f":"","\u7d44\u7e54\u5225\u540d\u7a31":"\u7368\u8cc7"}}}