{"data":{"\u767b\u8a18\u6a5f\u95dc":"\u5f70\u5316\u7e23\u653f\u5e9c","\u6838\u51c6\u8a2d\u7acb\u65e5\u671f":{"year":2017,"month":9,"day":25},"\u6700\u8fd1\u7570\u52d5\u65e5\u671f":{"year":2020,"month":1,"day":9},"\u5546\u696d\u540d\u7a31":"\u5b87\u6636\u6c7d\u8eca\u4fee\u914d\u5ee0","\u8ca0\u8cac\u4eba\u59d3\u540d":"\u694a\u7389\u5982","\u73fe\u6cc1":"\u6838\u51c6\u8a2d\u7acb","\u8cc7\u672c\u984d(\u5143)":"200,000","\u7d44\u7e54\u985e\u578b":"\u5408\u5925","\u5730\u5740":"\u5f70\u5316\u7e23\u6eaa\u6e56\u93ae\u897f\u6eaa\u91cc\u54e1\u9e7f\u8def2\u6bb5459\u5df717\u865f1\u6a13","\u71df\u696d\u9805\u76ee":"1\r\n\t\t\t\t\t\t\t\t\t\t\t\t\t\t\tJA01010\r\n\t\t\t\t\t\t\t\t\t\t\t\t\t\t\t\u6c7d\u8eca\u4fee\u7406\u696d\r\n\t\t\t\t\t\t\t\t\t\t\t\t\t\t\r\n\t\t\t\t\t\t\t\t\t\t\t\t\t\t\t2\r\n\t\t\t\t\t\t\t\t\t\t\t\t\t\t\tF114030\r\n\t\t\t\t\t\t\t\t\t\t\t\t\t\t\t\u6c7d\u3001\u6a5f\u8eca\u96f6\u4ef6\u914d\u5099\u6279\u767c\u696d\r\n\t\t\t\t\t\t\t\t\t\t\t\t\t\t\r\n\t\t\t\t\t\t\t\t\t\t\t\t\t\t\t3\r\n\t\t\t\t\t\t\t\t\t\t\t\t\t\t\tF214030\r\n\t\t\t\t\t\t\t\t\t\t\t\t\t\t\t\u6c7d\u3001\u6a5f\u8eca\u96f6\u4ef6\u914d\u5099\u96f6\u552e\u696d\r\n\t\t\t\t\t\t\t\t\t\t\t\t\t\t\r\n\t\t\t\t\t\t\t\t\t\t\t\t\t\t\t4\r\n\t\t\t\t\t\t\t\t\t\t\t\t\t\t\tJA01990\r\n\t\t\t\t\t\t\t\t\t\t\t\t\t\t\t\u5176\u4ed6\u6c7d\u8eca\u670d\u52d9\u696d\r\n\t\t\t\t\t\t\t\t\t\t\t\t\t\t\r\n\t\t\t\t\t\t\t\t\t\t\t\t\t\t\t5\r\n\t\t\t\t\t\t\t\t\t\t\t\t\t\t\tF114050\r\n\t\t\t\t\t\t\t\t\t\t\t\t\t\t\t\u8eca\u80ce\u6279\u767c\u696d\r\n\t\t\t\t\t\t\t\t\t\t\t\t\t\t\r\n\t\t\t\t\t\t\t\t\t\t\t\t\t\t\t6\r\n\t\t\t\t\t\t\t\t\t\t\t\t\t\t\tJA01020\r\n\t\t\t\t\t\t\t\t\t\t\t\t\t\t\t\u6c7d\u8eca\u62d6\u540a\u696d\r\n\t\t\t\t\t\t\t\t\t\t\t\t\t\t\r\n\t\t\t\t\t\t\t\t\t\t\t\t\t\t\t7\r\n\t\t\t\t\t\t\t\t\t\t\t\t\t\t\tZZ99999\r\n\t\t\t\t\t\t\t\t\t\t\t\t\t\t\t\u9664\u8a31\u53ef\u696d\u52d9\u5916\uff0c\u5f97\u7d93\u71df\u6cd5\u4ee4\u975e\u7981\u6b62\u6216\u9650\u5236\u4e4b\u696d\u52d9","\u5408\u5925\u4eba\u59d3\u540d":"\u9673\u9436\u656c","\u51fa\u8cc7\u984d(\u5143)":{"\u694a\u7389\u5982":"100000","\u9673\u9436\u656c":"100000"},"url":"\/fts\/query\/QueryBusmDetail\/queryBusmDetail.do?objectId=SEI3MjM4NzMwNjgzNzAwMDAwMDAwMDE0Nzk1Mzgx&banNo=72387306&banKey=83700000000014795381","\u8ca1\u653f\u90e8":{"\u71df\u696d\u4eba\u540d\u7a31":"\u5b87\u6636\u6c7d\u8eca\u4fee\u914d\u5ee0","\u8cc7\u672c\u984d":"200000","\u8a2d\u7acb\u65e5\u671f":{"year":2017,"month":9,"day":25},"\u4f7f\u7528\u7d71\u4e00\u767c\u7968":"Y","\u884c\u696d":[["951199","\u5176\u4ed6\u6c7d\u8eca\u7dad\u4fee"]],"\u71df\u696d\u5730\u5740":"\u5f70\u5316\u7e23\u6eaa\u6e56\u93ae\u897f\u6eaa\u91cc\u54e1\u9e7f\u8def\u4e8c\u6bb5\uff14\uff15\uff19\u5df7\uff11\uff17\u865f\uff11\u6a13","\u7e3d\u6a5f\u69cb\u7d71\u4e00\u7de8\u865f":"","\u7d44\u7e54\u5225\u540d\u7a31":"\u5408\u5925"}}}