{"data":{"\u767b\u8a18\u6a5f\u95dc":"\u81fa\u4e2d\u5e02\u653f\u5e9c","\u6838\u51c6\u8a2d\u7acb\u65e5\u671f":{"year":2003,"month":12,"day":8},"\u6700\u8fd1\u7570\u52d5\u65e5\u671f":{"year":2010,"month":6,"day":7},"\u5546\u696d\u540d\u7a31":"\u4e0a\u76ca\u9396\u5319\u884c","\u8ca0\u8cac\u4eba\u59d3\u540d":"\u738b\u540d\u8c50","\u73fe\u6cc1":"\u6838\u51c6\u8a2d\u7acb","\u8cc7\u672c\u984d(\u5143)":"100,000","\u7d44\u7e54\u985e\u578b":"\u7368\u8cc7","\u5730\u5740":"\u81fa\u4e2d\u5e02\u897f\u5c6f\u5340\u4f55\u5fb7\u91cc\u7518\u8085\u8def\u4e00\u6bb5\uff12\uff19\u865f\u4e00\u6a13","\u71df\u696d\u9805\u76ee":"1\r\n\r\n                    F201010\r\n\r\n                    \u8fb2\u7522\u54c1\u96f6\u552e\u696d\r\n\r\n              \r\n                    2\r\n\r\n                    F206010\r\n\r\n                    \u4e94\u91d1\u96f6\u552e\u696d\r\n\r\n              \r\n                    3\r\n\r\n                    JZ99160\r\n\r\n                    \u523b\u5370\u696d\r\n\r\n              \r\n                    4\r\n\r\n                    JZ99990\r\n\r\n                    \u672a\u5206\u985e\u5176\u4ed6\u670d\u52d9\u696d\uff08\u8a31\u53ef\u53ca\u9650\u5236\u696d\u52d9\u9664\u5916\uff09\r\n\r\n              \r\n                    5\r\n\r\n                    JZ99170\r\n\r\n                    \u9396\u5319\u696d\r\n\r\n              \r\n                    6\r\n\r\n                    J101040\r\n\r\n                    \u5ee2\u68c4\u7269\u8655\u7406\u696d\uff08\u61c9\u4fdf\u8fa6\u59a5\u8a31\u53ef\u57f7\u7167\u5f8c\u59cb\u5f97\u71df\u696d\uff09\r\n\r\n              \r\n                    7\r\n\r\n                    F201070\r\n\r\n                    \u82b1\u5349\u96f6\u552e\u696d","\u8ca1\u653f\u90e8":{"\u71df\u696d\u4eba\u540d\u7a31":"\u4e0a\u76ca\u9396\u5319\u884c","\u8cc7\u672c\u984d":"100000","\u8a2d\u7acb\u65e5\u671f":{"year":2003,"month":12,"day":9},"\u4f7f\u7528\u7d71\u4e00\u767c\u7968":"N","\u884c\u696d":[["969018","\u523b\u5370\u7ae0"],["472112","\u6c34\u679c\u96f6\u552e"],["959917","\u958b\u9396\u53ca\u914d\u9396"]],"\u71df\u696d\u5730\u5740":"\u81fa\u4e2d\u5e02\u897f\u5c6f\u5340\u4f55\u5fb7\u91cc\u7518\u8085\u8def\uff11\u6bb5\uff12\uff19\u865f\uff11\u6a13","\u8ca0\u8cac\u4eba\u59d3\u6c0f":"\u738b","\u7e3d\u6a5f\u69cb\u7d71\u4e00\u7de8\u865f":"","\u7d44\u7e54\u5225\u540d\u7a31":"\u7368\u8cc7"}}}