{"data":{"\u767b\u8a18\u6a5f\u95dc":"\u81fa\u5357\u5e02\u653f\u5e9c","\u6838\u51c6\u8a2d\u7acb\u65e5\u671f":{"year":2019,"month":12,"day":11},"\u6700\u8fd1\u7570\u52d5\u65e5\u671f":{"year":2019,"month":12,"day":11},"\u5546\u696d\u540d\u7a31":"\u5354\u7fa4\u767c\u4f01\u696d","\u8ca0\u8cac\u4eba\u59d3\u540d":"\u9ec3\u4fca\u537f","\u73fe\u6cc1":"\u6838\u51c6\u8a2d\u7acb","\u8cc7\u672c\u984d(\u5143)":"236,000","\u7d44\u7e54\u985e\u578b":"\u7368\u8cc7","\u5730\u5740":"\u81fa\u5357\u5e02\u65b0\u71df\u5340\u6c11\u69ae\u91cc\u65b0\u9032\u8def2\u6bb5500\u4e4b4\u865f7\u6a13","\u71df\u696d\u9805\u76ee":"1\r\n\t\t\t\t\t\t\t\t\t\t\t\t\t\t\tE601010\r\n\t\t\t\t\t\t\t\t\t\t\t\t\t\t\t\u96fb\u5668\u627f\u88dd\u696d\r\n\t\t\t\t\t\t\t\t\t\t\t\t\t\t\r\n\t\t\t\t\t\t\t\t\t\t\t\t\t\t\t2\r\n\t\t\t\t\t\t\t\t\t\t\t\t\t\t\tI503010\r\n\t\t\t\t\t\t\t\t\t\t\t\t\t\t\t\u666f\u89c0\u3001\u5ba4\u5167\u8a2d\u8a08\u696d\r\n\t\t\t\t\t\t\t\t\t\t\t\t\t\t\r\n\t\t\t\t\t\t\t\t\t\t\t\t\t\t\t3\r\n\t\t\t\t\t\t\t\t\t\t\t\t\t\t\tEZ99990\r\n\t\t\t\t\t\t\t\t\t\t\t\t\t\t\t\u5176\u4ed6\u5de5\u7a0b\u696d\r\n\t\t\t\t\t\t\t\t\t\t\t\t\t\t\r\n\t\t\t\t\t\t\t\t\t\t\t\t\t\t\t4\r\n\t\t\t\t\t\t\t\t\t\t\t\t\t\t\tF299990\r\n\t\t\t\t\t\t\t\t\t\t\t\t\t\t\t\u5176\u4ed6\u96f6\u552e\u696d\r\n\t\t\t\t\t\t\t\t\t\t\t\t\t\t\r\n\t\t\t\t\t\t\t\t\t\t\t\t\t\t\t5\r\n\t\t\t\t\t\t\t\t\t\t\t\t\t\t\tF213090\r\n\t\t\t\t\t\t\t\t\t\t\t\t\t\t\t\u4ea4\u901a\u6a19\u8a8c\u5668\u6750\u96f6\u552e\u696d\r\n\t\t\t\t\t\t\t\t\t\t\t\t\t\t\r\n\t\t\t\t\t\t\t\t\t\t\t\t\t\t\t6\r\n\t\t\t\t\t\t\t\t\t\t\t\t\t\t\tJ101030\r\n\t\t\t\t\t\t\t\t\t\t\t\t\t\t\t\u5ee2\u68c4\u7269\u6e05\u9664\u696d\r\n\t\t\t\t\t\t\t\t\t\t\t\t\t\t\r\n\t\t\t\t\t\t\t\t\t\t\t\t\t\t\t7\r\n\t\t\t\t\t\t\t\t\t\t\t\t\t\t\tIZ12010\r\n\t\t\t\t\t\t\t\t\t\t\t\t\t\t\t\u4eba\u529b\u6d3e\u9063\u696d\r\n\t\t\t\t\t\t\t\t\t\t\t\t\t\t\r\n\t\t\t\t\t\t\t\t\t\t\t\t\t\t\t8\r\n\t\t\t\t\t\t\t\t\t\t\t\t\t\t\tZZ99999\r\n\t\t\t\t\t\t\t\t\t\t\t\t\t\t\t\u9664\u8a31\u53ef\u696d\u52d9\u5916\uff0c\u5f97\u7d93\u71df\u6cd5\u4ee4\u975e\u7981\u6b62\u6216\u9650\u5236\u4e4b\u696d\u52d9","\u51fa\u8cc7\u984d(\u5143)":{"\u9ec3\u4fca\u537f":"236000"},"url":"\/fts\/query\/QueryBusmDetail\/queryBusmDetail.do?objectId=SEI4MTQ3MzIyNjYyMTAwMDAwMDAwMDE3NjE0MjM3&banNo=81473226&banKey=62100000000017614237","\u8ca1\u653f\u90e8":{"\u71df\u696d\u4eba\u540d\u7a31":"\u5354\u7fa4\u767c\u4f01\u696d","\u8cc7\u672c\u984d":"236000","\u8a2d\u7acb\u65e5\u671f":{"year":2019,"month":12,"day":11},"\u4f7f\u7528\u7d71\u4e00\u767c\u7968":"Y","\u884c\u696d":[["439099","\u672a\u5206\u985e\u5176\u4ed6\u5c08\u9580\u71df\u9020"],["433199","\u5176\u4ed6\u6a5f\u96fb\u3001\u96fb\u4fe1\u53ca\u96fb\u8def\u8a2d\u5099\u5b89\u88dd"],["711112","\u666f\u89c0\u5efa\u7bc9\u670d\u52d9"],["485299","\u672a\u5206\u985e\u5176\u4ed6\u5168\u65b0\u5546\u54c1\u96f6\u552e"]],"\u71df\u696d\u5730\u5740":"\u81fa\u5357\u5e02\u65b0\u71df\u5340\u6c11\u69ae\u91cc\uff10\uff11\uff15\u9130\u65b0\u9032\u8def\uff12\u6bb5\uff15\uff10\uff10\u2015\uff14\u865f\uff17\u6a13","\u7e3d\u6a5f\u69cb\u7d71\u4e00\u7de8\u865f":"","\u7d44\u7e54\u5225\u540d\u7a31":"\u7368\u8cc7"}}}