{"data":{"\u767b\u8a18\u6a5f\u95dc":"\u9ad8\u96c4\u5e02\u653f\u5e9c\u7d93\u6fdf\u767c\u5c55\u5c40","\u6838\u51c6\u8a2d\u7acb\u65e5\u671f":{"year":2019,"month":7,"day":8},"\u5546\u696d\u540d\u7a31":"\u548c\u8208\u96fb\u8a0a\u5de5\u7a0b\u884c","\u8ca0\u8cac\u4eba\u59d3\u540d":"\u5433\u66c9\u6674","\u73fe\u6cc1":"\u6838\u51c6\u8a2d\u7acb","\u8cc7\u672c\u984d(\u5143)":"200,000","\u7d44\u7e54\u985e\u578b":"\u7368\u8cc7","\u5730\u5740":"\u9ad8\u96c4\u5e02\u4e09\u6c11\u5340\u6176\u96f2\u8857117\u865f6\u6a13\u4e4b2","\u71df\u696d\u9805\u76ee":"1\n\r\n\t\t\t\t\t\t\tE701010\n\r\n\t\t\t\t\t\t\t\u96fb\u4fe1\u5de5\u7a0b\u696d\n\r\n\t\t\t\t\t\t\r\n\t\t\t\t\t\t\t2\n\r\n\t\t\t\t\t\t\tE701020\n\r\n\t\t\t\t\t\t\t\u885b\u661f\u96fb\u8996\uff2b\uff35\u983b\u9053\u3001\uff23\u983b\u9053\u5668\u6750\u5b89\u88dd\u696d\n\r\n\t\t\t\t\t\t\r\n\t\t\t\t\t\t\t3\n\r\n\t\t\t\t\t\t\tE701030\n\r\n\t\t\t\t\t\t\t\u96fb\u4fe1\u7ba1\u5236\u5c04\u983b\u5668\u6750\u88dd\u8a2d\u5de5\u7a0b\u696d\n\r\n\t\t\t\t\t\t\r\n\t\t\t\t\t\t\t4\n\r\n\t\t\t\t\t\t\tE701040\n\r\n\t\t\t\t\t\t\t\u7c21\u6613\u96fb\u4fe1\u8a2d\u5099\u5b89\u88dd\u696d\n\r\n\t\t\t\t\t\t\r\n\t\t\t\t\t\t\t5\n\r\n\t\t\t\t\t\t\tE603040\n\r\n\t\t\t\t\t\t\t\u6d88\u9632\u5b89\u5168\u8a2d\u5099\u5b89\u88dd\u5de5\u7a0b\u696d\n\r\n\t\t\t\t\t\t\r\n\t\t\t\t\t\t\t6\n\r\n\t\t\t\t\t\t\tE603050\n\r\n\t\t\t\t\t\t\t\u81ea\u52d5\u63a7\u5236\u8a2d\u5099\u5de5\u7a0b\u696d\n\r\n\t\t\t\t\t\t\r\n\t\t\t\t\t\t\t7\n\r\n\t\t\t\t\t\t\tE603080\n\r\n\t\t\t\t\t\t\t\u4ea4\u901a\u865f\u8a8c\u5b89\u88dd\u5de5\u7a0b\u696d\n\r\n\t\t\t\t\t\t\r\n\t\t\t\t\t\t\t8\n\r\n\t\t\t\t\t\t\tE605010\n\r\n\t\t\t\t\t\t\t\u96fb\u8166\u8a2d\u5099\u5b89\u88dd\u696d\n\r\n\t\t\t\t\t\t\r\n\t\t\t\t\t\t\t9\n\r\n\t\t\t\t\t\t\tEZ05010\n\r\n\t\t\t\t\t\t\t\u5100\u5668\u3001\u5100\u8868\u5b89\u88dd\u5de5\u7a0b\u696d\n\r\n\t\t\t\t\t\t\r\n\t\t\t\t\t\t\t10\n\r\n\t\t\t\t\t\t\tEZ99990\n\r\n\t\t\t\t\t\t\t\u5176\u4ed6\u5de5\u7a0b\u696d\n\r\n\t\t\t\t\t\t\r\n\t\t\t\t\t\t\t11\n\r\n\t\t\t\t\t\t\tF113070\n\r\n\t\t\t\t\t\t\t\u96fb\u4fe1\u5668\u6750\u6279\u767c\u696d\n\r\n\t\t\t\t\t\t\r\n\t\t\t\t\t\t\t12\n\r\n\t\t\t\t\t\t\tF113050\n\r\n\t\t\t\t\t\t\t\u96fb\u8166\u53ca\u4e8b\u52d9\u6027\u6a5f\u5668\u8a2d\u5099\u6279\u767c\u696d\n\r\n\t\t\t\t\t\t\r\n\t\t\t\t\t\t\t13\n\r\n\t\t\t\t\t\t\tF113090\n\r\n\t\t\t\t\t\t\t\u4ea4\u901a\u6a19\u8a8c\u5668\u6750\u6279\u767c\u696d\n\r\n\t\t\t\t\t\t\r\n\t\t\t\t\t\t\t14\n\r\n\t\t\t\t\t\t\tF118010\n\r\n\t\t\t\t\t\t\t\u8cc7\u8a0a\u8edf\u9ad4\u6279\u767c\u696d\n\r\n\t\t\t\t\t\t\r\n\t\t\t\t\t\t\t15\n\r\n\t\t\t\t\t\t\tF199990\n\r\n\t\t\t\t\t\t\t\u5176\u4ed6\u6279\u767c\u696d\n\r\n\t\t\t\t\t\t\r\n\t\t\t\t\t\t\t16\n\r\n\t\t\t\t\t\t\tF401010\n\r\n\t\t\t\t\t\t\t\u570b\u969b\u8cbf\u6613\u696d\n\r\n\t\t\t\t\t\t\r\n\t\t\t\t\t\t\t17\n\r\n\t\t\t\t\t\t\tZZ99999\n\r\n\t\t\t\t\t\t\t\u9664\u8a31\u53ef\u696d\u52d9\u5916\uff0c\u5f97\u7d93\u71df\u6cd5\u4ee4\u975e\u7981\u6b62\u6216\u9650\u5236\u4e4b\u696d\u52d9","\u51fa\u8cc7\u984d(\u5143)":{"\u5433\u66c9\u6674":"200000"},"\u7570\u52d5\u6838\u51c6\u65e5\u671f":{"year":2019,"month":7,"day":8},"\u8ca1\u653f\u90e8":{"\u71df\u696d\u4eba\u540d\u7a31":"\u548c\u8208\u96fb\u8a0a\u5de5\u7a0b\u884c","\u8cc7\u672c\u984d":"200000","\u8a2d\u7acb\u65e5\u671f":{"year":2019,"month":7,"day":8},"\u4f7f\u7528\u7d71\u4e00\u767c\u7968":"Y","\u884c\u696d":[["952200","\u901a\u8a0a\u50b3\u64ad\u8a2d\u5099\u7dad\u4fee"],["433112","\u96fb\u8def\u5de5\u7a0b"]],"\u71df\u696d\u5730\u5740":"\u9ad8\u96c4\u5e02\u4e09\u6c11\u5340\u5b89\u5409\u91cc\u6176\u96f2\u8857\uff11\uff11\uff17\u865f\uff16\u6a13\u4e4b\uff12","\u7e3d\u6a5f\u69cb\u7d71\u4e00\u7de8\u865f":"","\u7d44\u7e54\u5225\u540d\u7a31":"\u7368\u8cc7"}}}